metacommunity_diversity/__init__.py
metacommunity_diversity/__main__.py
metacommunity_diversity/abundance.py
metacommunity_diversity/components.py
metacommunity_diversity/exceptions.py
metacommunity_diversity/log.py
metacommunity_diversity/metacommunity.py
metacommunity_diversity/parameters.py
metacommunity_diversity/similarity.py
metacommunity_diversity/utilities.py
metacommunity_diversity-0.0.1.dist-info/METADATA
metacommunity_diversity-0.0.1.dist-info/WHEEL
metacommunity_diversity-0.0.1.dist-info/licenses/LICENSE
metacommunity_diversity-0.0.1.dist-info/RECORD
