Metadata-Version: 2.1
Name: metacommunity_diversity
Version: 0.0.1
Summary: A Python package for measuring the composition of complex datasets
Project-URL: Homepage, https://github.com/Elliot-D-Hill/diversity
Project-URL: Bug Tracker, https://github.com/Elliot-D-Hill/diversity/issues
Author: Jasper Braun
Author-email: Elliot Hill <elliot.douglas.hill@gmail.com>
License-File: LICENSE
Classifier: License :: OSI Approved :: MIT License
Classifier: Operating System :: OS Independent
Classifier: Programming Language :: Python :: 3
Requires-Python: >=3.8
Requires-Dist: numpy==1.24.0
Requires-Dist: pandas>=1.5.2
Requires-Dist: ray>=2.2.0
Requires-Dist: scipy==1.10.0
Provides-Extra: ci
Requires-Dist: tox-gh-actions>=2.9.1; extra == 'ci'
Requires-Dist: tox>=3.24.5; extra == 'ci'
Provides-Extra: lint
Requires-Dist: black>=22.3.0; extra == 'lint'
Provides-Extra: tests
Requires-Dist: pytest-cov>=3.0.0; extra == 'tests'
Requires-Dist: pytest>=6.2.5; extra == 'tests'
